peewee_utils/__init__.py
peewee_utils/main.py
peewee_utils-0.1.4.dist-info/LICENSE
peewee_utils-0.1.4.dist-info/METADATA
peewee_utils-0.1.4.dist-info/WHEEL
peewee_utils-0.1.4.dist-info/top_level.txt
peewee_utils-0.1.4.dist-info/RECORD
