Metadata-Version: 2.1
Name: peewee-utils
Version: 0.1.4
Summary: peewee utility, make prefetch result to dict without query
Home-page: https://github.com/negadive/peewee-utils
Author: Teguh Prabowo
Author-email: putr4.g4ul@gmail.com
License: UNKNOWN
Platform: UNKNOWN
Classifier: Programming Language :: Python :: 3
Classifier: License :: OSI Approved :: MIT License
Classifier: Operating System :: OS Independent
Classifier: Intended Audience :: Developers
Classifier: Topic :: Software Development :: Libraries :: Python Modules
Requires-Dist: peewee
